manim_plugintemplate/__init__.py
manim_plugintemplate/mobjects/__init__.py
manim_plugintemplate/mobjects/dotgrid.py
manim_plugintemplate-0.1.5.dist-info/entry_points.txt
manim_plugintemplate-0.1.5.dist-info/LICENSE.txt
manim_plugintemplate-0.1.5.dist-info/WHEEL
manim_plugintemplate-0.1.5.dist-info/METADATA
manim_plugintemplate-0.1.5.dist-info/RECORD
