Metadata-Version: 2.1
Name: manim-plugintemplate
Version: 0.1.5
Summary: A template project to both illustrate and serve as an example for plugin creations on top of the manim (community edition) engine.
Home-page: https://github.com/ManimCommunity/manim-plugintemplate
License: MIT
Author: The Manim Community Developers
Requires-Python: >=3.6.2,<4.0.0
Classifier: Development Status :: 4 - Beta
Classifier: License :: OSI Approved :: MIT License
Classifier: Natural Language :: English
Classifier: Programming Language :: Python :: 3
Classifier: Programming Language :: Python :: 3.6
Classifier: Programming Language :: Python :: 3.7
Classifier: Programming Language :: Python :: 3.8
Classifier: Programming Language :: Python :: 3.9
Classifier: Topic :: Multimedia :: Graphics
Classifier: Topic :: Multimedia :: Video
Classifier: Topic :: Scientific/Engineering
Requires-Dist: manim (>=0.3)
Project-URL: Documentation, https://docs.manim.community/en/latest/installation/plugins.html
Project-URL: Repository, https://github.com/ManimCommunity/manim-plugintemplate
